networkml/NetworkML.py
networkml/__init__.py
networkml/__main__.py
networkml/algorithms/__init__.py
networkml/algorithms/host_footprint.py
networkml/featurizers/README.md
networkml/featurizers/__init__.py
networkml/featurizers/csv_to_features.py
networkml/featurizers/features.py
networkml/featurizers/main.py
networkml/featurizers/funcs/__init__.py
networkml/featurizers/funcs/flow.py
networkml/featurizers/funcs/generic.py
networkml/featurizers/funcs/host.py
networkml/featurizers/funcs/packet.py
networkml/helpers/__init__.py
networkml/helpers/gzipio.py
networkml/helpers/pandas_csv_importer.py
networkml/helpers/results_output.py
networkml/parsers/__init__.py
networkml/parsers/pcap_to_csv.py
networkml/trained_models/README.md
networkml/trained_models/host_footprint.json
networkml/trained_models/host_footprint_le.json
networkml/trained_models/host_footprint_scaler.mod
networkml/trained_models/label_assignments.json
networkml-0.6.19.dist-info/AUTHORS
networkml-0.6.19.dist-info/LICENSE
networkml-0.6.19.dist-info/METADATA
networkml-0.6.19.dist-info/WHEEL
networkml-0.6.19.dist-info/entry_points.txt
networkml-0.6.19.dist-info/pbr.json
networkml-0.6.19.dist-info/top_level.txt
networkml-0.6.19.dist-info/RECORD
