Metadata-Version: 2.1
Name: networkml
Version: 0.6.19
Summary: Device Functional Role ID via Machine Learning and Network Traffic Analysis
Home-page: https://github.com/IQTLabs/NetworkML
Author: cglewis
Author-email: clewis@iqt.org
License: Apache-2
Platform: any
Classifier: Development Status :: 5 - Production/Stable
Classifier: License :: OSI Approved :: Apache Software License
Classifier: Programming Language :: Python
Requires-Python: >=3.6
Requires-Dist: cython (==0.29.28)
Requires-Dist: humanize (==4.0.0)
Requires-Dist: joblib (==1.1.0)
Requires-Dist: netaddr (==0.8.0)
Requires-Dist: numpy (==1.22.3)
Requires-Dist: pandas (==1.4.1)
Requires-Dist: pbr (==5.8.1)
Requires-Dist: pyshark (==0.4.5)
Requires-Dist: scikit-learn (==1.0.2)
